Workbook

Sheet Ventas_Edicion1
A1: ID_Venta | B1: Fecha | C1: ID_Cliente | D1: ID_Producto | E1: Producto | F1: Categoria | G1: Cantidad | H1: Precio_unitario | I1: Descuento | J1: Tipo_pago | K1: ID_Vendedor | L1: Sucursal
A2: {=+"V"&"-"&TEXT(_xlfn.SEQUENCE(5000),"0000")} -> V-0001 | B2: =+RANDBETWEEN("01/01/2025","31/12/2025") -> 45872 | C2: =+"C"&"-"&TEXT(RANDBETWEEN(1,4),"000") -> C-002 | D2: =+"P"&"-"&TEXT(RANDBETWEEN(1,4),"000") -> P-004 | E2: =+_xlfn.XLOOKUP(D2,'Tablas aux'!$A$3:$A$6,'Tablas aux'!$B$3:$B$6,0) -> Smart Phone | F2: =+_xlfn.XLOOKUP(E2,'Tablas aux'!$B$3:$B$6,'Tablas aux'!$C$3:$C$6,0) -> Telefonía | G2: =+RANDBETWEEN(5,45) -> 39 | H2: =+_xlfn.XLOOKUP(D2,'Tablas aux'!$A$3:$A$6,'Tablas aux'!$D$3:$D$6) -> 800 | I2: =+IF(F2="Electrónica",0.1,IF(F2="Telefonía",0.2,0.3)) -> 0.2 | J2: {=+INDEX({"Tarjeta";"Efectivo";"Transferencia"},RANDBETWEEN(1,3))} -> Transferencia | K2: =+"V"&"-"&TEXT(RANDBETWEEN(1,5),"000") -> V-001 | L2: =+VLOOKUP(K2,'Tablas aux'!$A$23:$C$27,3,0) -> Lima
A3: V-0002 | B3: =+RANDBETWEEN("01/01/2025","31/12/2025") -> 45926 | C3: =+"C"&"-"&TEXT(RANDBETWEEN(1,4),"000") -> C-002 | D3: =+"P"&"-"&TEXT(RANDBETWEEN(1,4),"000") -> P-004 | E3: =+_xlfn.XLOOKUP(D3,'Tablas aux'!$A$3:$A$6,'Tablas aux'!$B$3:$B$6,0) -> Smart Phone | F3: =+_xlfn.XLOOKUP(E3,'Tablas aux'!$B$3:$B$6,'Tablas aux'!$C$3:$C$6,0) -> Telefonía | G3: =+RANDBETWEEN(5,45) -> 29 | H3: =+_xlfn.XLOOKUP(D3,'Tablas aux'!$A$3:$A$6,'Tablas aux'!$D$3:$D$6) -> 800 | I3: =+IF(F3="Electrónica",0.1,IF(F3="Telefonía",0.2,0.3)) -> 0.2 | J3: {=+INDEX({"Tarjeta";"Efectivo";"Transferencia"},RANDBETWEEN(1,3))} -> Transferencia | K3: =+"V"&"-"&TEXT(RANDBETWEEN(1,5),"000") -> V-005 | L3: =+VLOOKUP(K3,'Tablas aux'!$A$23:$C$27,3,0) -> Ayacucho
A4: V-0003 | B4: =+RANDBETWEEN("01/01/2025","31/12/2025") -> 45848 | C4: =+"C"&"-"&TEXT(RANDBETWEEN(1,4),"000") -> C-004 | D4: =+"P"&"-"&TEXT(RANDBETWEEN(1,4),"000") -> P-001 | E4: =+_xlfn.XLOOKUP(D4,'Tablas aux'!$A$3:$A$6,'Tablas aux'!$B$3:$B$6,0) -> Audífonos | F4: =+_xlfn.XLOOKUP(E4,'Tablas aux'!$B$3:$B$6,'Tablas aux'!$C$3:$C$6,0) -> Electrónica | G4: =+RANDBETWEEN(5,45) -> 10 | H4: =+_xlfn.XLOOKUP(D4,'Tablas aux'!$A$3:$A$6,'Tablas aux'!$D$3:$D$6) -> 50 | I4: =+IF(F4="Electrónica",0.1,IF(F4="Telefonía",0.2,0.3)) -> 0.1 | J4: {=+INDEX({"Tarjeta";"Efectivo";"Transferencia"},RANDBETWEEN(1,3))} -> Transferencia | K4: =+"V"&"-"&TEXT(RANDBETWEEN(1,5),"000") -> V-003 | L4: =+VLOOKUP(K4,'Tablas aux'!$A$23:$C$27,3,0) -> Arequipa
A5: V-0004 | B5: =+RANDBETWEEN("01/01/2025","31/12/2025") -> 45925 | C5: =+"C"&"-"&TEXT(RANDBETWEEN(1,4),"000") -> C-002 | D5: =+"P"&"-"&TEXT(RANDBETWEEN(1,4),"000") -> P-003 | E5: =+_xlfn.XLOOKUP(D5,'Tablas aux'!$A$3:$A$6,'Tablas aux'!$B$3:$B$6,0) -> Smart Watch | F5: =+_xlfn.XLOOKUP(E5,'Tablas aux'!$B$3:$B$6,'Tablas aux'!$C$3:$C$6,0) -> Electrónica | G5: =+RANDBETWEEN(5,45) -> 15 | H5: =+_xlfn.XLOOKUP(D5,'Tablas aux'!$A$3:$A$6,'Tablas aux'!$D$3:$D$6) -> 200 | I5: =+IF(F5="Electrónica",0.1,IF(F5="Telefonía",0.2,0.3)) -> 0.1 | J5: {=+INDEX({"Tarjeta";"Efectivo";"Transferencia"},RANDBETWEEN(1,3))} -> Tarjeta | K5: =+"V"&"-"&TEXT(RANDBETWEEN(1,5),"000") -> V-003 | L5: =+VLOOKUP(K5,'Tablas aux'!$A$23:$C$27,3,0) -> Arequipa
A6: V-0005 | B6: =+RANDBETWEEN("01/01/2025","31/12/2025") -> 45790 | C6: =+"C"&"-"&TEXT(RANDBETWEEN(1,4),"000") -> C-001 | D6: =+"P"&"-"&TEXT(RANDBETWEEN(1,4),"000") -> P-002 | E6: =+_xlfn.XLOOKUP(D6,'Tablas aux'!$A$3:$A$6,'Tablas aux'!$B$3:$B$6,0) -> Laptop | F6: =+_xlfn.XLOOKUP(E6,'Tablas aux'!$B$3:$B$6,'Tablas aux'!$C$3:$C$6,0) -> Computo | G6: =+RANDBETWEEN(5,45) -> 22 | H6: =+_xlfn.XLOOKUP(D6,'Tablas aux'!$A$3:$A$6,'Tablas aux'!$D$3:$D$6) -> 1200 | I6: =+IF(F6="Electrónica",0.1,IF(F6="Telefonía",0.2,0.3)) -> 0.3 | J6: {=+INDEX({"Tarjeta";"Efectivo";"Transferencia"},RANDBETWEEN(1,3))} -> Efectivo | K6: =+"V"&"-"&TEXT(RANDBETWEEN(1,5),"000") -> V-005 | L6: =+VLOOKUP(K6,'Tablas aux'!$A$23:$C$27,3,0) -> Ayacucho
A7: V-0006 | B7: =+RANDBETWEEN("01/01/2025","31/12/2025") -> 45731 | C7: =+"C"&"-"&TEXT(RANDBETWEEN(1,4),"000") -> C-001 | D7: =+"P"&"-"&TEXT(RANDBETWEEN(1,4),"000") -> P-004 | E7: =+_xlfn.XLOOKUP(D7,'Tablas aux'!$A$3:$A$6,'Tablas aux'!$B$3:$B$6,0) -> Smart Phone | F7: =+_xlfn.XLOOKUP(E7,'Tablas aux'!$B$3:$B$6,'Tablas aux'!$C$3:$C$6,0) -> Telefonía | G7: =+RANDBETWEEN(5,45) -> 35 | H7: =+_xlfn.XLOOKUP(D7,'Tablas aux'!$A$3:$A$6,'Tablas aux'!$D$3:$D$6) -> 800 | I7: =+IF(F7="Electrónica",0.1,IF(F7="Telefonía",0.2,0.3)) -> 0.2 | J7: {=+INDEX({"Tarjeta";"Efectivo";"Transferencia"},RANDBETWEEN(1,3))} -> Tarjeta | K7: =+"V"&"-"&TEXT(RANDBETWEEN(1,5),"000") -> V-004 | L7: =+VLOOKUP(K7,'Tablas aux'!$A$23:$C$27,3,0) -> Moquegua
A8: V-0007 | B8: =+RANDBETWEEN("01/01/2025","31/12/2025") -> 45888 | C8: =+"C"&"-"&TEXT(RANDBETWEEN(1,4),"000") -> C-003 | D8: =+"P"&"-"&TEXT(RANDBETWEEN(1,4),"000") -> P-003 | E8: =+_xlfn.XLOOKUP(D8,'Tablas aux'!$A$3:$A$6,'Tablas aux'!$B$3:$B$6,0) -> Smart Watch | F8: =+_xlfn.XLOOKUP(E8,'Tablas aux'!$B$3:$B$6,'Tablas aux'!$C$3:$C$6,0) -> Electrónica | G8: =+RANDBETWEEN(5,45) -> 25 | H8: =+_xlfn.XLOOKUP(D8,'Tablas aux'!$A$3:$A$6,'Tablas aux'!$D$3:$D$6) -> 200 | I8: =+IF(F8="Electrónica",0.1,IF(F8="Telefonía",0.2,0.3)) -> 0.1 | J8: {=+INDEX({"Tarjeta";"Efectivo";"Transferencia"},RANDBETWEEN(1,3))} -> Tarjeta | K8: =+"V"&"-"&TEXT(RANDBETWEEN(1,5),"000") -> V-003 | L8: =+VLOOKUP(K8,'Tablas aux'!$A$23:$C$27,3,0) -> Arequipa
A9: V-0008 | B9: =+RANDBETWEEN("01/01/2025","31/12/2025") -> 45941 | C9: =+"C"&"-"&TEXT(RANDBETWEEN(1,4),"000") -> C-001 | D9: =+"P"&"-"&TEXT(RANDBETWEEN(1,4),"000") -> P-004 | E9: =+_xlfn.XLOOKUP(D9,'Tablas aux'!$A$3:$A$6,'Tablas aux'!$B$3:$B$6,0) -> Smart Phone | F9: =+_xlfn.XLOOKUP(E9,'Tablas aux'!$B$3:$B$6,'Tablas aux'!$C$3:$C$6,0) -> Telefonía | G9: =+RANDBETWEEN(5,45) -> 7 | H9: =+_xlfn.XLOOKUP(D9,'Tablas aux'!$A$3:$A$6,'Tablas aux'!$D$3:$D$6) -> 800 | I9: =+IF(F9="Electrónica",0.1,IF(F9="Telefonía",0.2,0.3)) -> 0.2 | J9: {=+INDEX({"Tarjeta";"Efectivo";"Transferencia"},RANDBETWEEN(1,3))} -> Transferencia | K9: =+"V"&"-"&TEXT(RANDBETWEEN(1,5),"000") -> V-005 | L9: =+VLOOKUP(K9,'Tablas aux'!$A$23:$C$27,3,0) -> Ayacucho
A10: V-0009 | B10: =+RANDBETWEEN("01/01/2025","31/12/2025") -> 46020 | C10: =+"C"&"-"&TEXT(RANDBETWEEN(1,4),"000") -> C-003 | D10: =+"P"&"-"&TEXT(RANDBETWEEN(1,4),"000") -> P-004 | E10: =+_xlfn.XLOOKUP(D10,'Tablas aux'!$A$3:$A$6,'Tablas aux'!$B$3:$B$6,0) -> Smart Phone | F10: =+_xlfn.XLOOKUP(E10,'Tablas aux'!$B$3:$B$6,'Tablas aux'!$C$3:$C$6,0) -> Telefonía | G10: =+RANDBETWEEN(5,45) -> 18 | H10: =+_xlfn.XLOOKUP(D10,'Tablas aux'!$A$3:$A$6,'Tablas aux'!$D$3:$D$6) -> 800 | I10: =+IF(F10="Electrónica",0.1,IF(F10="Telefonía",0.2,0.3)) -> 0.2 | J10: {=+INDEX({"Tarjeta";"Efectivo";"Transferencia"},RANDBETWEEN(1,3))} -> Efectivo | K10: =+"V"&"-"&TEXT(RANDBETWEEN(1,5),"000") -> V-004 | L10: =+VLOOKUP(K10,'Tablas aux'!$A$23:$C$27,3,0) -> Moquegua
A11: V-0010 | B11: =+RANDBETWEEN("01/01/2025","31/12/2025") -> 45828 | C11: =+"C"&"-"&TEXT(RANDBETWEEN(1,4),"000") -> C-001 | D11: =+"P"&"-"&TEXT(RANDBETWEEN(1,4),"000") -> P-002 | E11: =+_xlfn.XLOOKUP(D11,'Tablas aux'!$A$3:$A$6,'Tablas aux'!$B$3:$B$6,0) -> Laptop | F11: =+_xlfn.XLOOKUP(E11,'Tablas aux'!$B$3:$B$6,'Tablas aux'!$C$3:$C$6,0) -> Computo | G11: =+RANDBETWEEN(5,45) -> 32 | H11: =+_xlfn.XLOOKUP(D11,'Tablas aux'!$A$3:$A$6,'Tablas aux'!$D$3:$D$6) -> 1200 | I11: =+IF(F11="Electrónica",0.1,IF(F11="Telefonía",0.2,0.3)) -> 0.3 | J11: {=+INDEX({"Tarjeta";"Efectivo";"Transferencia"},RANDBETWEEN(1,3))} -> Transferencia | K11: =+"V"&"-"&TEXT(RANDBETWEEN(1,5),"000") -> V-003 | L11: =+VLOOKUP(K11,'Tablas aux'!$A$23:$C$27,3,0) -> Arequipa
A12: V-0011 | B12: =+RANDBETWEEN("01/01/2025","31/12/2025") -> 45673 | C12: =+"C"&"-"&TEXT(RANDBETWEEN(1,4),"000") -> C-002 | D12: =+"P"&"-"&TEXT(RANDBETWEEN(1,4),"000") -> P-001 | E12: =+_xlfn.XLOOKUP(D12,'Tablas aux'!$A$3:$A$6,'Tablas aux'!$B$3:$B$6,0) -> Audífonos | F12: =+_xlfn.XLOOKUP(E12,'Tablas aux'!$B$3:$B$6,'Tablas aux'!$C$3:$C$6,0) -> Electrónica | G12: =+RANDBETWEEN(5,45) -> 18 | H12: =+_xlfn.XLOOKUP(D12,'Tablas aux'!$A$3:$A$6,'Tablas aux'!$D$3:$D$6) -> 50 | I12: =+IF(F12="Electrónica",0.1,IF(F12="Telefonía",0.2,0.3)) -> 0.1 | J12: {=+INDEX({"Tarjeta";"Efectivo";"Transferencia"},RANDBETWEEN(1,3))} -> Transferencia | K12: =+"V"&"-"&TEXT(RANDBETWEEN(1,5),"000") -> V-004 | L12: =+VLOOKUP(K12,'Tablas aux'!$A$23:$C$27,3,0) -> Moquegua
A13: V-0012 | B13: =+RANDBETWEEN("01/01/2025","31/12/2025") -> 46018 | C13: =+"C"&"-"&TEXT(RANDBETWEEN(1,4),"000") -> C-003 | D13: =+"P"&"-"&TEXT(RANDBETWEEN(1,4),"000") -> P-004 | E13: =+_xlfn.XLOOKUP(D13,'Tablas aux'!$A$3:$A$6,'Tablas aux'!$B$3:$B$6,0) -> Smart Phone | F13: =+_xlfn.XLOOKUP(E13,'Tablas aux'!$B$3:$B$6,'Tablas aux'!$C$3:$C$6,0) -> Telefonía | G13: =+RANDBETWEEN(5,45) -> 9 | H13: =+_xlfn.XLOOKUP(D13,'Tablas aux'!$A$3:$A$6,'Tablas aux'!$D$3:$D$6) -> 800 | I13: =+IF(F13="Electrónica",0.1,IF(F13="Telefonía",0.2,0.3)) -> 0.2 | J13: {=+INDEX({"Tarjeta";"Efectivo";"Transferencia"},RANDBETWEEN(1,3))} -> Tarjeta | K13: =+"V"&"-"&TEXT(RANDBETWEEN(1,5),"000") -> V-004 | L13: =+VLOOKUP(K13,'Tablas aux'!$A$23:$C$27,3,0) -> Moquegua
A14: V-0013 | B14: =+RANDBETWEEN("01/01/2025","31/12/2025") -> 45683 | C14: =+"C"&"-"&TEXT(RANDBETWEEN(1,4),"000") -> C-002 | D14: =+"P"&"-"&TEXT(RANDBETWEEN(1,4),"000") -> P-001 | E14: =+_xlfn.XLOOKUP(D14,'Tablas aux'!$A$3:$A$6,'Tablas aux'!$B$3:$B$6,0) -> Audífonos | F14: =+_xlfn.XLOOKUP(E14,'Tablas aux'!$B$3:$B$6,'Tablas aux'!$C$3:$C$6,0) -> Electrónica | G14: =+RANDBETWEEN(5,45) -> 12 | H14: =+_xlfn.XLOOKUP(D14,'Tablas aux'!$A$3:$A$6,'Tablas aux'!$D$3:$D$6) -> 50 | I14: =+IF(F14="Electrónica",0.1,IF(F14="Telefonía",0.2,0.3)) -> 0.1 | J14: {=+INDEX({"Tarjeta";"Efectivo";"Transferencia"},RANDBETWEEN(1,3))} -> Tarjeta | K14: =+"V"&"-"&TEXT(RANDBETWEEN(1,5),"000") -> V-002 | L14: =+VLOOKUP(K14,'Tablas aux'!$A$23:$C$27,3,0) -> Callao
... A5001: V-5000 | B5001: =+RANDBETWEEN("01/01/2025","31/12/2025") -> 45739 | C5001: =+"C"&"-"&TEXT(RANDBETWEEN(1,4),"000") -> C-003 | D5001: =+"P"&"-"&TEXT(RANDBETWEEN(1,4),"000") -> P-004 | E5001: =+_xlfn.XLOOKUP(D5001,'Tablas aux'!$A$3:$A$6,'Tablas aux'!$B$3:$B$6,0) -> Smart Phone | F5001: =+_xlfn.XLOOKUP(E5001,'Tablas aux'!$B$3:$B$6,'Tablas aux'!$C$3:$C$6,0) -> Telefonía | G5001: =+RANDBETWEEN(5,45) -> 5 | H5001: =+_xlfn.XLOOKUP(D5001,'Tablas aux'!$A$3:$A$6,'Tablas aux'!$D$3:$D$6) -> 800 | I5001: =+IF(F5001="Electrónica",0.1,IF(F5001="Telefonía",0.2,0.3)) -> 0.2 | J5001: {=+INDEX({"Tarjeta";"Efectivo";"Transferencia"},RANDBETWEEN(1,3))} -> Tarjeta | K5001: =+"V"&"-"&TEXT(RANDBETWEEN(1,5),"000") -> V-005 | L5001: =+VLOOKUP(K5001,'Tablas aux'!$A$23:$C$27,3,0) -> Ayacucho

Sheet Tablas aux
A1: TABLA PRODUCTOS
A2: ID Producto | B2: Nombre Producto | C2: Categoría | D2: Precio Unitario | E2: Stock Actual
A3: P-001 | B3: Audífonos | C3: Electrónica | D3: 50 | E3: 120
A4: P-002 | B4: Laptop | C4: Computo | D4: 1200 | E4: 35
A5: P-003 | B5: Smart Watch | C5: Electrónica | D5: 200 | E5: 80
A6: P-004 | B6: Smart Phone | C6: Telefonía | D6: 800 | E6: 50
A13: TABLA CLIENTES
A14: ID Cliente | B14: Nombre Cliente | C14: Edad | D14: Género | E14: Ciudad | F14: Segmento
A15: C-001 | B15: María López | C15: 25 | D15: F | E15: Lima | F15: Joven
A16: C-002 | B16: Pedro Torres | C16: 40 | D16: M | E16: Callao | F16: Adulto
A17: C-003 | B17: Carla Gómez | C17: 33 | D17: F | E17: Arequipa | F17: Adulto
A18: C-004 | B18: Sofía Mayta | C18: 20 | D18: F | E18: Tacna | F18: Joven
A21: TABLA VENDEDOR
A22: ID Vendedor | B22: Nombre Vendedor | C22: Región | D22: Meta Mensual
A23: V-001 | B23: Juan Pérez | C23: Lima | D23: 5000
A24: V-002 | B24: Ana Ramírez | C24: Callao | D24: 7000
A25: V-003 | B25: Luis Fernández | C25: Arequipa | D25: 4000
A26: V-004 | B26: Keyla Mendoza | C26: Moquegua | D26: 6500
A27: V-005 | B27: Andy Quintana | C27: Ayacucho | D27: 3500

Sheet Ventas_final
A1: ID_Venta | B1: Fecha | C1: ID_Cliente | D1: ID_Producto | E1: Producto | F1: Categoria | G1: Cantidad | H1: Precio_unitario | I1: Descuento | J1: Tipo_pago | K1: ID_Vendedor | L1: Sucursal | M1: Venta_Total
A2: V-0001 | B2: 45909 | C2: C-001 | D2: P-003 | E2: Smart Watch | F2: Electrónica | G2: 13 | H2: 200 | I2: 0.1 | J2: Tarjeta | K2: V-005 | L2: Ayacucho | M2: =+TablaVentas[[#This Row],[Cantidad]]*TablaVentas[[#This Row],[Precio_unitario]]*(1-TablaVentas[[#This Row],[Descuento]]) -> 2340
A3: V-0002 | B3: 46009 | C3: C-001 | D3: P-004 | E3: Smart Phone | F3: Telefonía | G3: 34 | H3: 800 | I3: 0.2 | J3: Efectivo | K3: V-005 | L3: Ayacucho | M3: =+TablaVentas[[#This Row],[Cantidad]]*TablaVentas[[#This Row],[Precio_unitario]]*(1-TablaVentas[[#This Row],[Descuento]]) -> 21760
A4: V-0003 | B4: 45895 | C4: C-003 | D4: P-001 | E4: Audífonos | F4: Electrónica | G4: 5 | H4: 50 | I4: 0.1 | J4: Transferencia | K4: V-001 | L4: Lima | M4: =+TablaVentas[[#This Row],[Cantidad]]*TablaVentas[[#This Row],[Precio_unitario]]*(1-TablaVentas[[#This Row],[Descuento]]) -> 225
A5: V-0004 | B5: 45732 | C5: C-002 | D5: P-001 | E5: Audífonos | F5: Electrónica | G5: 15 | H5: 50 | I5: 0.1 | J5: Transferencia | K5: V-003 | L5: Arequipa | M5: =+TablaVentas[[#This Row],[Cantidad]]*TablaVentas[[#This Row],[Precio_unitario]]*(1-TablaVentas[[#This Row],[Descuento]]) -> 675
A6: V-0005 | B6: 45694 | C6: C-003 | D6: P-002 | E6: Laptop | F6: Computo | G6: 44 | H6: 1200 | I6: 0.3 | J6: Tarjeta | K6: V-004 | L6: Moquegua | M6: =+TablaVentas[[#This Row],[Cantidad]]*TablaVentas[[#This Row],[Precio_unitario]]*(1-TablaVentas[[#This Row],[Descuento]]) -> 36960
A7: V-0006 | B7: 45863 | C7: C-001 | D7: P-003 | E7: Smart Watch | F7: Electrónica | G7: 21 | H7: 200 | I7: 0.1 | J7: Tarjeta | K7: V-004 | L7: Moquegua | M7: =+TablaVentas[[#This Row],[Cantidad]]*TablaVentas[[#This Row],[Precio_unitario]]*(1-TablaVentas[[#This Row],[Descuento]]) -> 3780
A8: V-0007 | B8: 45931 | C8: C-002 | D8: P-001 | E8: Audífonos | F8: Electrónica | G8: 43 | H8: 50 | I8: 0.1 | J8: Efectivo | K8: V-005 | L8: Ayacucho | M8: =+TablaVentas[[#This Row],[Cantidad]]*TablaVentas[[#This Row],[Precio_unitario]]*(1-TablaVentas[[#This Row],[Descuento]]) -> 1935
A9: V-0008 | B9: 45961 | C9: C-001 | D9: P-004 | E9: Smart Phone | F9: Telefonía | G9: 16 | H9: 800 | I9: 0.2 | J9: Transferencia | K9: V-005 | L9: Ayacucho | M9: =+TablaVentas[[#This Row],[Cantidad]]*TablaVentas[[#This Row],[Precio_unitario]]*(1-TablaVentas[[#This Row],[Descuento]]) -> 10240
A10: V-0009 | B10: 45747 | C10: C-004 | D10: P-001 | E10: Audífonos | F10: Electrónica | G10: 40 | H10: 50 | I10: 0.1 | J10: Tarjeta | K10: V-005 | L10: Ayacucho | M10: =+TablaVentas[[#This Row],[Cantidad]]*TablaVentas[[#This Row],[Precio_unitario]]*(1-TablaVentas[[#This Row],[Descuento]]) -> 1800
A11: V-0010 | B11: 45895 | C11: C-003 | D11: P-002 | E11: Laptop | F11: Computo | G11: 25 | H11: 1200 | I11: 0.3 | J11: Tarjeta | K11: V-001 | L11: Lima | M11: =+TablaVentas[[#This Row],[Cantidad]]*TablaVentas[[#This Row],[Precio_unitario]]*(1-TablaVentas[[#This Row],[Descuento]]) -> 21000
A12: V-0011 | B12: 45779 | C12: C-004 | D12: P-001 | E12: Audífonos | F12: Electrónica | G12: 43 | H12: 50 | I12: 0.1 | J12: Tarjeta | K12: V-001 | L12: Lima | M12: =+TablaVentas[[#This Row],[Cantidad]]*TablaVentas[[#This Row],[Precio_unitario]]*(1-TablaVentas[[#This Row],[Descuento]]) -> 1935
A13: V-0012 | B13: 45925 | C13: C-004 | D13: P-001 | E13: Audífonos | F13: Electrónica | G13: 9 | H13: 50 | I13: 0.1 | J13: Tarjeta | K13: V-005 | L13: Ayacucho | M13: =+TablaVentas[[#This Row],[Cantidad]]*TablaVentas[[#This Row],[Precio_unitario]]*(1-TablaVentas[[#This Row],[Descuento]]) -> 405
... A5001: V-5000 | B5001: 45712 | C5001: C-002 | D5001: P-003 | E5001: Smart Watch | F5001: Electrónica | G5001: 18 | H5001: 200 | I5001: 0.1 | J5001: Tarjeta | K5001: V-002 | L5001: Callao | M5001: =+TablaVentas[[#This Row],[Cantidad]]*TablaVentas[[#This Row],[Precio_unitario]]*(1-TablaVentas[[#This Row],[Descuento]]) -> 3240

Sheet Resumen
A1: VENTAS POR SUCURSAL | B1: Ventas totales
A2: Ayacucho | B2: =+SUMIF(TablaVentas[Sucursal],"Ayacucho",TablaVentas[Venta_Total]) -> 10644860
A3: Arequipa | B3: =+SUMIF(TablaVentas[Sucursal],A3,TablaVentas[Venta_Total]) -> 10892765
A4: Moquegua | B4: =+SUMIF(TablaVentas[Sucursal],A4,TablaVentas[Venta_Total]) -> 10490245
A5: Lima | B5: =+SUMIF(TablaVentas[Sucursal],A5,TablaVentas[Venta_Total]) -> 10635700
A6: Callao | B6: =+SUMIF(TablaVentas[Sucursal],A6,TablaVentas[Venta_Total]) -> 10621870
E8: Etiquetas de fila | F8: Suma de Venta_Total
A9: VENTAS POR SUCURSAL Y CATEGORIA = Electronica | E9: Arequipa | F9: 10892765
A10: Ayacucho | B10: =+SUMIFS(TablaVentas[Venta_Total],TablaVentas[Sucursal],A10,TablaVentas[Categoria],"Electrónica") -> 1515060 | E10: Computo | F10: 5657400
A11: Arequipa | B11: =+SUMIFS(TablaVentas[Venta_Total],TablaVentas[Sucursal],A11,TablaVentas[Categoria],"Electrónica") -> 1415205 | E11: Electrónica | F11: 1415205
A12: Moquegua | B12: =+SUMIFS(TablaVentas[Venta_Total],TablaVentas[Sucursal],A12,TablaVentas[Categoria],"Electrónica") -> 1421685 | E12: Telefonía | F12: 3820160
A13: Lima | B13: =+SUMIFS(TablaVentas[Venta_Total],TablaVentas[Sucursal],A13,TablaVentas[Categoria],"Electrónica") -> 1322820 | E13: Ayacucho | F13: 10644860
A14: Callao | B14: =+SUMIFS(TablaVentas[Venta_Total],TablaVentas[Sucursal],A14,TablaVentas[Categoria],"Electrónica") -> 1345950 | E14: Computo | F14: 5309640
E15: Electrónica | F15: 1515060
E16: Telefonía | F16: 3820160
A17: VENTAS POR SUCURSAL Y CATEGORIA = Computo | E17: Callao | F17: 10621870
A18: Ayacucho | B18: =+SUMIFS(TablaVentas[Venta_Total],TablaVentas[Sucursal],A18,TablaVentas[Categoria],"Computo") -> 5309640 | E18: Computo | F18: 5216400
A19: Arequipa | B19: =+SUMIFS(TablaVentas[Venta_Total],TablaVentas[Sucursal],A19,TablaVentas[Categoria],"Computo") -> 5657400 | E19: Electrónica | F19: 1345950
A20: Moquegua | B20: =+SUMIFS(TablaVentas[Venta_Total],TablaVentas[Sucursal],A20,TablaVentas[Categoria],"Computo") -> 5444880 | E20: Telefonía | F20: 4059520
A21: Lima | B21: =+SUMIFS(TablaVentas[Venta_Total],TablaVentas[Sucursal],A21,TablaVentas[Categoria],"Computo") -> 5118960 | E21: Lima | F21: 10635700
A22: Callao | B22: =+SUMIFS(TablaVentas[Venta_Total],TablaVentas[Sucursal],A22,TablaVentas[Categoria],"Computo") -> 5216400 | E22: Computo | F22: 5118960
E23: Electrónica | F23: 1322820
E24: Telefonía | F24: 4193920
E25: Moquegua | F25: 10490245
E26: Computo | F26: 5444880
E27: Electrónica | F27: 1421685
E28: Telefonía | F28: 3623680
E29: Total general | F29: 53285440
